outbound
