Metadata-Version: 1.0
Name: outbound
Version: 1.2.0
Summary: Outbound sends automated email, SMS, phone calls and push notifications based on the actions users take (or do not take) in your app.
Home-page: https://github.com/outboundio/lib-python
Author: Outbound.io
Author-email: support@segment.io
License: MIT License
Platform: UNKNOWN
